{"cache_key": "6b71b2be2af1a74d3c89db028e4dcdd0-procdump", "data": [["m", {"session": {"state": {"profile": ["nt/GUID/2BCBB42C1BC741DF9E1D4E2D28DAC9631", "FileName"], "timezone": ["UTC", "TimeZone"], "ept": [null, "IntParser"], "pagefile": [[], "FileName"], "session_name": ["Windows Server 2012", "String"], "filename": ["../images/Windows_Server-2012-R2_RTM-English-64Bit-Base-2015.02.11.aff4", "FileName"]}, "mro": "InteractiveSession:JsonSerializableSession:Session:object", "id": 160, "session_id": 1}, "cookie": 819327, "tool_name": "rekall", "plugin_name": "None", "tool_version": "1.3.0"}], ["m", {"session": {"state": {"profile": ["nt/GUID/2BCBB42C1BC741DF9E1D4E2D28DAC9631", "FileName"], "timezone": ["UTC", "TimeZone"], "ept": [null, "IntParser"], "pagefile": [[], "FileName"], "session_name": ["Windows Server 2012", "String"], "filename": ["../images/Windows_Server-2012-R2_RTM-English-64Bit-Base-2015.02.11.aff4", "FileName"]}, "mro": "InteractiveSession:JsonSerializableSession:Session:object", "id": 160, "session_id": 1}, "cookie": 819327, "tool_name": "rekall", "plugin_name": "procdump", "tool_version": "1.3.0"}], ["s", {"name": null}], ["f", "Dumping {0}, pid: {1:6} output: {2}\n", "LiteAgent.exe", 1152, "executable.LiteAgent_exe_1152.exe"], ["file", "executable.LiteAgent_exe_1152.exe", "1427499279630/executable.LiteAgent_exe_1152.exe"], ["x"], ["x"]]}